LICENSE
MANIFEST.in
README.rst
requirements.txt
setup.cfg
setup.py
./brittle_wit_core/__init__.py
./brittle_wit_core/common.py
./brittle_wit_core/oauth.py
./test/__init__.py
./test/conftest.py
./test/test_app_credentials.py
./test/test_client_credentials.py
./test/test_cursoring.py
./test/test_error_types.py
./test/test_oauth_flow.py
./test/test_oauth_helpers.py
./test/test_requests.py
brittle_wit_core.egg-info/PKG-INFO
brittle_wit_core.egg-info/SOURCES.txt
brittle_wit_core.egg-info/dependency_links.txt
brittle_wit_core.egg-info/requires.txt
brittle_wit_core.egg-info/top_level.txt
test/test_app_credentials.py
test/test_client_credentials.py
test/test_cursoring.py
test/test_error_types.py
test/test_oauth_flow.py
test/test_oauth_helpers.py
test/test_requests.py