Metadata-Version: 1.1
Name: brittle-wit-core
Version: 0.0.4
Summary: Version-agnostic core for brittle_wit package
Home-page: https://github.com/jbn/brittle_wit_core
Author: John Bjorn Nelson
Author-email: jbn@abreka.com
License: MIT
Keywords: twitter,twitter api,social networks
Platform: UNKNOWN
Classifier: Development Status :: 3 - Alpha
Classifier: Framework :: IPython
Classifier: Topic :: Communications
Classifier: Natural Language :: English
Classifier: License :: OSI Approved :: MIT License
Classifier: Operating System :: OS Independent
Classifier: Programming Language :: Python :: 2.7
Classifier: Programming Language :: Python :: 3.4
Classifier: Programming Language :: Python :: 3.5
Classifier: Topic :: Software Development :: Libraries :: Python Modules
